{
  "main": {
    "id": "25772d47d6f7b3df",
    "type": "split",
    "children": [
      {
        "id": "abd370afde4237e8",
        "type": "tabs",
        "children": [
          {
            "id": "360e6e002d651e60",
            "type": "leaf",
            "state": {
              "type": "markdown",
              "state": {
                "file": "Support/Shariyl/Core UI/Primitives/Chainable Frame.md",
                "mode": "source",
                "source": false
              }
            }
          },
          {
            "id": "f955d4a028cfcc4c",
            "type": "leaf",
            "state": {
              "type": "markdown",
              "state": {
                "file": "Support/Shariyl/Core UI/Generic Text/Text Generic.md",
                "mode": "source",
                "source": false
              }
            }
          },
          {
            "id": "fc180ef43ab2f680",
            "type": "leaf",
            "state": {
              "type": "markdown",
              "state": {
                "file": "_Templates/Package.md",
                "mode": "source",
                "source": false
              }
            }
          },
          {
            "id": "af0a299dfbd173cf",
            "type": "leaf",
            "state": {
              "type": "markdown",
              "state": {
                "file": "Support/Shariyl/Core/Camera.md",
                "mode": "source",
                "source": false
              }
            }
          },
          {
            "id": "97bf61fb5251d5d1",
            "type": "leaf",
            "state": {
              "type": "markdown",
              "state": {
                "file": "Support/Shariyl/Core UI/Primitives/Frame.md",
                "mode": "source",
                "source": false
              }
            }
          }
        ],
        "currentTab": 3
      }
    ],
    "direction": "vertical"
  },
  "left": {
    "id": "9396fadfbbb8fcc1",
    "type": "split",
    "children": [
      {
        "id": "d81fb440200eca5c",
        "type": "tabs",
        "children": [
          {
            "id": "3218d0d294ddecb3",
            "type": "leaf",
            "state": {
              "type": "file-explorer",
              "state": {
                "sortOrder": "alphabetical"
              }
            }
          },
          {
            "id": "3c3ef6da8f16bace",
            "type": "leaf",
            "state": {
              "type": "search",
              "state": {
                "query": "",
                "matchingCase": false,
                "explainSearch": false,
                "collapseAll": false,
                "extraContext": false,
                "sortOrder": "alphabetical"
              }
            }
          },
          {
            "id": "92886420c41dcf48",
            "type": "leaf",
            "state": {
              "type": "bookmarks",
              "state": {}
            }
          }
        ]
      }
    ],
    "direction": "horizontal",
    "width": 356.5
  },
  "right": {
    "id": "451e3e34dfabc95c",
    "type": "split",
    "children": [
      {
        "id": "79d685ea29664bac",
        "type": "tabs",
        "children": [
          {
            "id": "5fc9d74915bd00c2",
            "type": "leaf",
            "state": {
              "type": "backlink",
              "state": {
                "file": "Support/Shariyl/Core/Camera.md",
                "collapseAll": false,
                "extraContext": false,
                "sortOrder": "alphabetical",
                "showSearch": false,
                "searchQuery": "",
                "backlinkCollapsed": false,
                "unlinkedCollapsed": true
              }
            }
          },
          {
            "id": "6acc2cc5f72c46cc",
            "type": "leaf",
            "state": {
              "type": "outgoing-link",
              "state": {
                "file": "Support/Shariyl/Core/Camera.md",
                "linksCollapsed": false,
                "unlinkedCollapsed": true
              }
            }
          },
          {
            "id": "7dfec1c01ab6cc6a",
            "type": "leaf",
            "state": {
              "type": "tag",
              "state": {
                "sortOrder": "frequency",
                "useHierarchy": true
              }
            }
          },
          {
            "id": "4d64d2987c2afd3f",
            "type": "leaf",
            "state": {
              "type": "outline",
              "state": {
                "file": "Support/Shariyl/Core/Camera.md"
              }
            }
          },
          {
            "id": "e7f5f2a9254e06d1",
            "type": "leaf",
            "state": {
              "type": "advanced-tables-toolbar",
              "state": {}
            }
          }
        ],
        "currentTab": 4
      }
    ],
    "direction": "horizontal",
    "width": 300,
    "collapsed": true
  },
  "left-ribbon": {
    "hiddenItems": {
      "switcher:Open quick switcher": false,
      "graph:Open graph view": false,
      "canvas:Create new canvas": false,
      "daily-notes:Open today's daily note": false,
      "templates:Insert template": false,
      "command-palette:Open command palette": false,
      "table-editor-obsidian:Advanced Tables Toolbar": false
    }
  },
  "active": "af0a299dfbd173cf",
  "lastOpenFiles": [
    "Support/Shariyl/Core/Event Broker.md",
    "Support/Shariyl/Core/Reference.md",
    "Support/Shariyl/Core/_Core.md",
    "Support/Shariyl/Core/Camera.md",
    "Support/Shariyl/Core UI/_Core UI.md",
    "Support/Shariyl/Core/System Alarm.md",
    "_Templates/Package.md",
    "out/plantuml/event_broker/Event Broker.png",
    "out/plantuml/event_broker",
    "out/plantuml/training_menu/Spawn In General.png",
    "out/plantuml/training_menu/asd.png",
    "plantuml/event_broker.puml",
    "Support/Shariyl/Core UI/_Contracts/Macros.md",
    "Support/Shariyl/Core/_Contracts/HasTrigger.md",
    "Support/Shariyl/Core/_Contracts/HasTransform.md",
    "Support/Shariyl/Core/_Contracts",
    "Random Canvas/Poll and Emit.canvas",
    "Attachments/Poll and Emit.png",
    "Support/Shariyl/Core UI/Lists/List Menu.md",
    "Random Canvas/List Menu.canvas",
    "Random Canvas/Frame With Control Stack Explanation.canvas",
    "Attachments/List Menu.png",
    "Random Canvas/Untitled.canvas",
    "Support/Shariyl/Core UI/Primitives/Frame With Control Stack.md",
    "Support/Shariyl/Core UI/Lists/List Item.md",
    "Attachments/Frame With Control Stack Explanation.png",
    "Attachments",
    "New folder",
    "Support/Shariyl/Core UI/Primitives/Point2D.md",
    "Support/Shariyl/Core UI/Primitives/Frame.md",
    "Support/Shariyl/Core UI/Primitives/Chainable Frame.md",
    "Support/Shariyl/Core UI/Decorator",
    "Support/Shariyl/Core UI/Generic Text",
    "Support/Shariyl/Core UI/Primitives",
    "Support/Shariyl/Core UI/Lists",
    "Support/Shariyl/Core UI/Lists/List Menu 2D.md",
    "Support/Shariyl/Core UI/Window Tabs.md",
    "Pasted image 20240726111735.png",
    "Random Canvas",
    "Untitled.md",
    "Pasted image 20240719204240.png",
    "Pasted image 20240718120908.png",
    "Za Todos.md",
    "Camera Analysis.png",
    "index.md",
    "Support/Shariyl/Data Structures/List.md",
    "2024-07-04.md",
    "Support/Standards/option.md",
    "Support/Shariyl/Data Structures/HashMap.md",
    "_Templates/Object.md",
    "Support/Shariyl/Dependency Graph.canvas",
    "Dependency Graph.canvas",
    "Untitled/Untitled.canvas"
  ]
}